google_yubikey/__init__.py
google_yubikey/__main__.py
google_yubikey/device.py
google_yubikey/metadata.py
google_yubikey/util.py
google_yubikey-0.4.11.dist-info/LICENSE.md
google_yubikey-0.4.11.dist-info/METADATA
google_yubikey-0.4.11.dist-info/WHEEL
google_yubikey-0.4.11.dist-info/entry_points.txt
google_yubikey-0.4.11.dist-info/top_level.txt
google_yubikey-0.4.11.dist-info/RECORD
