Metadata-Version: 2.1
Name: google-yubikey
Version: 0.4.11
Summary: Generate Google Service Account tokens with your YubiKey
Home-page: https://github.com/dinvlad/google-yubikey
Author: Denis Loginov
License: BSD 3-clause "New" or "Revised" License
Platform: UNKNOWN
Classifier: Development Status :: 3 - Alpha
Classifier: License :: OSI Approved :: BSD License
Classifier: Operating System :: OS Independent
Classifier: Programming Language :: Python :: 3 :: Only
Classifier: Topic :: Security
Classifier: Topic :: Security :: Cryptography
Classifier: Topic :: Utilities
Requires-Python: >=3.7.0
Requires-Dist: flask (>=1.1.2)
Requires-Dist: python-hosts (>=1.0.0)
Requires-Dist: requests (>=2.24.0)
Requires-Dist: six (>=1.15.0)
Requires-Dist: uwsgi (>=2.0.19.1)
Requires-Dist: yubikey-manager (>=3.1.1)
